{
  "type": "object",
  "properties": {
    "name": {
      "type": "string"
    },
    "features": {
      "type": "array",
      "items": [
        {
          "type": "object",
          "properties": {
            "label": {
              "type": "string"
            },
            "value": {
              "type": "string"
            },
            "roles": {
              "type": "array",
              "items": [
                {
                  "type": "string"
                }
              ]
            }
          },
          "required": ["label", "value", "roles"]
        }
      ]
    }
  },
  "required": ["name", "features"]
}
